PwnAssistor/__init__.py
PwnAssistor/attacker/__init__.py
PwnAssistor/attacker/fmt.py
PwnAssistor/attacker/gadget.py
PwnAssistor/attacker/heap.py
PwnAssistor/attacker/io.py
PwnAssistor/attacker/pwnvar.py
PwnAssistor/attacker/stack.py
PwnAssistor-0.2.0.dist-info/LICENSE
PwnAssistor-0.2.0.dist-info/METADATA
PwnAssistor-0.2.0.dist-info/WHEEL
PwnAssistor-0.2.0.dist-info/top_level.txt
PwnAssistor-0.2.0.dist-info/RECORD
