Metadata-Version: 2.1
Name: PwnAssistor
Version: 0.2.0
Summary: Atool for pwn
Author: V3rdant
License: MIT
Classifier: Programming Language :: Python :: 3
Classifier: License :: OSI Approved :: MIT License
Classifier: Operating System :: OS Independent
Requires: pwntools
License-File: LICENSE
